aws_tgw_details/__init__.py
aws_tgw_details/__init__.pyi
aws_tgw_details/__main__.py
aws_tgw_details/__main__.pyi
aws_tgw_details/py.typed
aws_tgw_details-1.0.18.data/scripts/aws_tgws
aws_tgw_details-1.0.18.dist-info/METADATA
aws_tgw_details-1.0.18.dist-info/WHEEL
aws_tgw_details-1.0.18.dist-info/entry_points.txt
aws_tgw_details-1.0.18.dist-info/RECORD
