Metadata-Version: 2.1
Name: aws_tgw_details
Version: 1.0.18
Summary: Get AWS Transit Gateway details.
Home-page: https://gitlab.com/fer1035_python/modules/pypi-aws_tgw_details
License: GPL-2.0-only
Keywords: aws,transit,gateway,vpc,network
Author: Ahmad Ferdaus Abd Razak
Author-email: fer1035@gmail.com
Requires-Python: >=3.9,<4.0
Classifier: License :: OSI Approved :: GNU General Public License v2 (GPLv2)
Classifier: Programming Language :: Python :: 3
Classifier: Programming Language :: Python :: 3.9
Classifier: Programming Language :: Python :: 3.10
Classifier: Programming Language :: Python :: 3.11
Classifier: Programming Language :: Python :: 3.12
Requires-Dist: aws_authenticator (>=2.0.2,<3.0.0)
Project-URL: Repository, https://gitlab.com/fer1035_python/modules/pypi-aws_tgw_details
